{
    "type": "FlightsCollection",
    "flights": [
        {
            "type": "flight",
            "order": 1,
            "from": "PER",
            "to": "ARG",
            "status": true,
            "startLat": -9.941004,
            "startLng": -76.514508,
            "endLat": -31.116022,
            "endLng": -64.100630,
            "arcAlt": 0.2
        },
        {
            "type": "flight",
            "order": 2,
            "from": "PER",
            "to": "EU",
            "status": true,
            "startLat": -9.941004,
            "startLng": -76.514508,
            "endLat": 38.252817,
            "endLng": -101.013016,
            "arcAlt": 0.2
        },
        {
            "type": "flight",
            "order": 3,
            "from": "PER",
            "to": "ESP",
            "status": true,
            "startLat": -9.941004,
            "startLng": -76.514508,
            "endLat": 39.742069,
            "endLng": -4.197894,
            "arcAlt": 0.2
        }
    ]
}